{"moduleDefinition":{"range":[1,1,1,75],"value":{"type":"normal","normal":{"moduleName":{"range":[1,8,1,19],"value":["ViewPlanner"]},"exposingList":{"range":[1,20,1,75],"value":{"type":"explicit","explicit":[{"range":[1,30,1,35],"value":{"type":"typeOrAlias","typeOrAlias":{"name":"Model"}}},{"range":[1,37,1,40],"value":{"type":"typeOrAlias","typeOrAlias":{"name":"Msg"}}},{"range":[1,42,1,46],"value":{"type":"function","function":{"name":"init"}}},{"range":[1,48,1,60],"value":{"type":"function","function":{"name":"initialModel"}}},{"range":[1,62,1,68],"value":{"type":"function","function":{"name":"update"}}},{"range":[1,70,1,74],"value":{"type":"function","function":{"name":"view"}}}]}}}}},"imports":[{"range":[3,1,3,34],"value":{"moduleName":{"range":[3,8,3,24],"value":["Bootstrap","Button"]},"moduleAlias":{"range":[3,28,3,34],"value":["Button"]},"exposingList":null}},{"range":[4,1,4,43],"value":{"moduleName":{"range":[4,8,4,21],"value":["Bootstrap","CDN"]},"moduleAlias":null,"exposingList":{"range":[4,22,4,43],"value":{"type":"explicit","explicit":[{"range":[4,32,4,42],"value":{"type":"function","function":{"name":"stylesheet"}}}]}}}},{"range":[5,1,5,30],"value":{"moduleName":{"range":[5,8,5,22],"value":["Bootstrap","Grid"]},"moduleAlias":{"range":[5,26,5,30],"value":["Grid"]},"exposingList":null}},{"range":[6,1,6,33],"value":{"moduleName":{"range":[6,8,6,26],"value":["Browser","Navigation"]},"moduleAlias":{"range":[6,30,6,33],"value":["Nav"]},"exposingList":null}},{"range":[7,1,7,28],"value":{"moduleName":{"range":[7,8,7,12],"value":["Dict"]},"moduleAlias":null,"exposingList":{"range":[7,13,7,28],"value":{"type":"explicit","explicit":[{"range":[7,23,7,27],"value":{"type":"typeOrAlias","typeOrAlias":{"name":"Dict"}}}]}}}},{"range":[8,1,8,42],"value":{"moduleName":{"range":[8,8,8,13],"value":["Error"]},"moduleAlias":null,"exposingList":{"range":[8,14,8,42],"value":{"type":"explicit","explicit":[{"range":[8,24,8,41],"value":{"type":"function","function":{"name":"buildErrorMessage"}}}]}}}},{"range":[9,1,9,26],"value":{"moduleName":{"range":[9,8,9,12],"value":["Html"]},"moduleAlias":null,"exposingList":{"range":[9,13,9,26],"value":{"type":"all","all":[9,23,9,25]}}}},{"range":[10,1,10,37],"value":{"moduleName":{"range":[10,8,10,23],"value":["Html","Attributes"]},"moduleAlias":null,"exposingList":{"range":[10,24,10,37],"value":{"type":"all","all":[10,34,10,36]}}}},{"range":[11,1,11,33],"value":{"moduleName":{"range":[11,8,11,19],"value":["Html","Events"]},"moduleAlias":null,"exposingList":{"range":[11,20,11,33],"value":{"type":"all","all":[11,30,11,32]}}}},{"range":[12,1,12,12],"value":{"moduleName":{"range":[12,8,12,12],"value":["Http"]},"moduleAlias":null,"exposingList":null}},{"range":[13,1,13,29],"value":{"moduleName":{"range":[13,8,13,15],"value":["Planner"]},"moduleAlias":null,"exposingList":{"range":[13,16,13,29],"value":{"type":"all","all":[13,26,13,28]}}}},{"range":[14,1,14,37],"value":{"moduleName":{"range":[14,8,14,18],"value":["RemoteData"]},"moduleAlias":null,"exposingList":{"range":[14,19,14,37],"value":{"type":"explicit","explicit":[{"range":[14,29,14,36],"value":{"type":"typeOrAlias","typeOrAlias":{"name":"WebData"}}}]}}}},{"range":[15,1,15,13],"value":{"moduleName":{"range":[15,8,15,13],"value":["Route"]},"moduleAlias":null,"exposingList":null}}],"declarations":[{"range":[18,1,22,6],"value":{"type":"typeAlias","typeAlias":{"documentation":null,"name":{"range":[18,12,18,17],"value":"Model"},"generics":[],"typeAnnotation":{"range":[19,5,22,6],"value":{"type":"record","record":{"value":[{"range":[19,7,19,23],"value":{"name":{"range":[19,7,19,13],"value":"navKey"},"typeAnnotation":{"range":[19,16,19,23],"value":{"type":"typed","typed":{"moduleNameAndName":{"range":[19,16,19,23],"value":{"moduleName":["Nav"],"name":"Key"}},"args":[]}}}}},{"range":[20,5,21,5],"value":{"name":{"range":[20,7,20,14],"value":"planner"},"typeAnnotation":{"range":[20,17,20,32],"value":{"type":"typed","typed":{"moduleNameAndName":{"range":[20,17,20,24],"value":{"moduleName":[],"name":"WebData"}},"args":[{"range":[20,25,20,32],"value":{"type":"typed","typed":{"moduleNameAndName":{"range":[20,25,20,32],"value":{"moduleName":[],"name":"Planner"}},"args":[]}}}]}}}}},{"range":[21,5,22,5],"value":{"name":{"range":[21,7,21,16],"value":"saveError"},"typeAnnotation":{"range":[21,19,21,31],"value":{"type":"typed","typed":{"moduleNameAndName":{"range":[21,19,21,24],"value":{"moduleName":[],"name":"Maybe"}},"args":[{"range":[21,25,21,31],"value":{"type":"typed","typed":{"moduleNameAndName":{"range":[21,25,21,31],"value":{"moduleName":[],"name":"String"}},"args":[]}}}]}}}}}]}}}}}},{"range":[25,1,29,51],"value":{"type":"typedecl","typedecl":{"documentation":null,"name":{"range":[25,6,25,9],"value":"Msg"},"generics":[],"constructors":[{"range":[26,7,26,40],"value":{"name":{"range":[26,7,26,22],"value":"PlannerReceived"},"arguments":[{"range":[26,23,26,40],"value":{"type":"typed","typed":{"moduleNameAndName":{"range":[26,24,26,31],"value":{"moduleName":[],"name":"WebData"}},"args":[{"range":[26,32,26,39],"value":{"type":"typed","typed":{"moduleNameAndName":{"range":[26,32,26,39],"value":{"moduleName":[],"name":"Planner"}},"args":[]}}}]}}}]}},{"range":[27,7,27,38],"value":{"name":{"range":[27,7,27,24],"value":"SelectAppointment"},"arguments":[{"range":[27,25,27,31],"value":{"type":"typed","typed":{"moduleNameAndName":{"range":[27,25,27,31],"value":{"moduleName":[],"name":"String"}},"args":[]}}},{"range":[27,32,27,38],"value":{"type":"typed","typed":{"moduleNameAndName":{"range":[27,32,27,38],"value":{"moduleName":[],"name":"String"}},"args":[]}}}]}},{"range":[28,7,28,22],"value":{"name":{"range":[28,7,28,22],"value":"SaveAppointment"},"arguments":[]}},{"range":[29,7,29,51],"value":{"name":{"range":[29,7,29,23],"value":"AppointmentSaved"},"arguments":[{"range":[29,24,29,51],"value":{"type":"typed","typed":{"moduleNameAndName":{"range":[29,25,29,31],"value":{"moduleName":[],"name":"Result"}},"args":[{"range":[29,32,29,42],"value":{"type":"typed","typed":{"moduleNameAndName":{"range":[29,32,29,42],"value":{"moduleName":["Http"],"name":"Error"}},"args":[]}}},{"range":[29,43,29,50],"value":{"type":"typed","typed":{"moduleNameAndName":{"range":[29,43,29,50],"value":{"moduleName":[],"name":"Planner"}},"args":[]}}}]}}}]}}]}}},{"range":[32,1,37,6],"value":{"type":"function","function":{"documentation":null,"signature":{"range":[32,1,32,32],"value":{"name":{"range":[32,1,32,13],"value":"initialModel"},"typeAnnotation":{"range":[32,16,32,32],"value":{"type":"function","function":{"left":{"range":[32,16,32,23],"value":{"type":"typed","typed":{"moduleNameAndName":{"range":[32,16,32,23],"value":{"moduleName":["Nav"],"name":"Key"}},"args":[]}}},"right":{"range":[32,27,32,32],"value":{"type":"typed","typed":{"moduleNameAndName":{"range":[32,27,32,32],"value":{"moduleName":[],"name":"Model"}},"args":[]}}}}}}}},"declaration":{"range":[33,1,37,6],"value":{"name":{"range":[33,1,33,13],"value":"initialModel"},"arguments":[{"range":[33,14,33,20],"value":{"type":"var","var":{"value":"navKey"}}}],"expression":{"range":[34,5,37,6],"value":{"type":"record","record":[{"range":[34,7,34,22],"value":{"field":{"range":[34,7,34,13],"value":"navKey"},"expression":{"range":[34,16,34,22],"value":{"type":"functionOrValue","functionOrValue":{"moduleName":[],"name":"navKey"}}}}},{"range":[35,7,36,5],"value":{"field":{"range":[35,7,35,14],"value":"planner"},"expression":{"range":[35,17,35,35],"value":{"type":"functionOrValue","functionOrValue":{"moduleName":["RemoteData"],"name":"Loading"}}}}},{"range":[36,7,37,5],"value":{"field":{"range":[36,7,36,16],"value":"saveError"},"expression":{"range":[36,19,36,26],"value":{"type":"functionOrValue","functionOrValue":{"moduleName":[],"name":"Nothing"}}}}}]}}}}}}},{"range":[40,1,42,52],"value":{"type":"function","function":{"documentation":null,"signature":{"range":[40,1,40,47],"value":{"name":{"range":[40,1,40,5],"value":"init"},"typeAnnotation":{"range":[40,8,40,47],"value":{"type":"function","function":{"left":{"range":[40,8,40,14],"value":{"type":"typed","typed":{"moduleNameAndName":{"range":[40,8,40,14],"value":{"moduleName":[],"name":"String"}},"args":[]}}},"right":{"range":[40,18,40,47],"value":{"type":"function","function":{"left":{"range":[40,18,40,25],"value":{"type":"typed","typed":{"moduleNameAndName":{"range":[40,18,40,25],"value":{"moduleName":["Nav"],"name":"Key"}},"args":[]}}},"right":{"range":[40,29,40,47],"value":{"type":"tupled","tupled":{"values":[{"range":[40,31,40,36],"value":{"type":"typed","typed":{"moduleNameAndName":{"range":[40,31,40,36],"value":{"moduleName":[],"name":"Model"}},"args":[]}}},{"range":[40,38,40,45],"value":{"type":"typed","typed":{"moduleNameAndName":{"range":[40,38,40,41],"value":{"moduleName":[],"name":"Cmd"}},"args":[{"range":[40,42,40,45],"value":{"type":"typed","typed":{"moduleNameAndName":{"range":[40,42,40,45],"value":{"moduleName":[],"name":"Msg"}},"args":[]}}}]}}}]}}}}}}}}}}},"declaration":{"range":[41,1,42,52],"value":{"name":{"range":[41,1,41,5],"value":"init"},"arguments":[{"range":[41,6,41,15],"value":{"type":"var","var":{"value":"plannerId"}}},{"range":[41,16,41,22],"value":{"type":"var","var":{"value":"navKey"}}}],"expression":{"range":[42,5,42,52],"value":{"type":"tupled","tupled":[{"range":[42,7,42,26],"value":{"type":"application","application":[{"range":[42,7,42,19],"value":{"type":"functionOrValue","functionOrValue":{"moduleName":[],"name":"initialModel"}}},{"range":[42,20,42,26],"value":{"type":"functionOrValue","functionOrValue":{"moduleName":[],"name":"navKey"}}}]}},{"range":[42,28,42,50],"value":{"type":"application","application":[{"range":[42,28,42,40],"value":{"type":"functionOrValue","functionOrValue":{"moduleName":[],"name":"fetchPlanner"}}},{"range":[42,41,42,50],"value":{"type":"functionOrValue","functionOrValue":{"moduleName":[],"name":"plannerId"}}}]}}]}}}}}}},{"range":[45,1,89,14],"value":{"type":"function","function":{"documentation":null,"signature":{"range":[45,1,45,44],"value":{"name":{"range":[45,1,45,7],"value":"update"},"typeAnnotation":{"range":[45,10,45,44],"value":{"type":"function","function":{"left":{"range":[45,10,45,13],"value":{"type":"typed","typed":{"moduleNameAndName":{"range":[45,10,45,13],"value":{"moduleName":[],"name":"Msg"}},"args":[]}}},"right":{"range":[45,17,45,44],"value":{"type":"function","function":{"left":{"range":[45,17,45,22],"value":{"type":"typed","typed":{"moduleNameAndName":{"range":[45,17,45,22],"value":{"moduleName":[],"name":"Model"}},"args":[]}}},"right":{"range":[45,26,45,44],"value":{"type":"tupled","tupled":{"values":[{"range":[45,28,45,33],"value":{"type":"typed","typed":{"moduleNameAndName":{"range":[45,28,45,33],"value":{"moduleName":[],"name":"Model"}},"args":[]}}},{"range":[45,35,45,42],"value":{"type":"typed","typed":{"moduleNameAndName":{"range":[45,35,45,38],"value":{"moduleName":[],"name":"Cmd"}},"args":[{"range":[45,39,45,42],"value":{"type":"typed","typed":{"moduleNameAndName":{"range":[45,39,45,42],"value":{"moduleName":[],"name":"Msg"}},"args":[]}}}]}}}]}}}}}}}}}}},"declaration":{"range":[46,1,89,14],"value":{"name":{"range":[46,1,46,7],"value":"update"},"arguments":[{"range":[46,8,46,11],"value":{"type":"var","var":{"value":"msg"}}},{"range":[46,12,46,17],"value":{"type":"var","var":{"value":"model"}}}],"expression":{"range":[47,5,89,14],"value":{"type":"case","case":{"cases":[{"pattern":{"range":[48,9,48,33],"value":{"type":"named","named":{"qualified":{"moduleName":[],"name":"PlannerReceived"},"patterns":[{"range":[48,25,48,33],"value":{"type":"var","var":{"value":"response"}}}]}}},"expression":{"range":[49,13,49,57],"value":{"type":"tupled","tupled":[{"range":[49,15,49,45],"value":{"type":"recordUpdate","recordUpdate":{"name":{"range":[49,17,49,22],"value":"model"},"updates":[{"range":[49,25,49,44],"value":{"field":{"range":[49,25,49,32],"value":"planner"},"expression":{"range":[49,35,49,43],"value":{"type":"functionOrValue","functionOrValue":{"moduleName":[],"name":"response"}}}}}]}}},{"range":[49,47,49,55],"value":{"type":"functionOrValue","functionOrValue":{"moduleName":["Cmd"],"name":"none"}}}]}}},{"pattern":{"range":[51,9,51,36],"value":{"type":"named","named":{"qualified":{"moduleName":[],"name":"SelectAppointment"},"patterns":[{"range":[51,27,51,30],"value":{"type":"var","var":{"value":"key"}}},{"range":[51,31,51,36],"value":{"type":"var","var":{"value":"value"}}}]}}},"expression":{"range":[52,13,74,9],"value":{"type":"let","let":{"declarations":[{"range":[53,17,61,17],"value":{"type":"function","function":{"documentation":null,"signature":null,"declaration":{"range":[53,17,58,38],"value":{"name":{"range":[53,17,53,30],"value":"updatePlanner"},"arguments":[],"expression":{"range":[54,21,58,38],"value":{"type":"application","application":[{"range":[54,21,54,35],"value":{"type":"functionOrValue","functionOrValue":{"moduleName":["RemoteData"],"name":"map"}}},{"range":[55,25,57,26],"value":{"type":"parenthesized","parenthesized":{"range":[55,26,57,25],"value":{"type":"lambda","lambda":{"patterns":[{"range":[55,27,55,38],"value":{"type":"var","var":{"value":"plannerData"}}}],"expression":{"range":[56,29,56,117],"value":{"type":"recordUpdate","recordUpdate":{"name":{"range":[56,31,56,42],"value":"plannerData"},"updates":[{"range":[56,45,56,116],"value":{"field":{"range":[56,45,56,57],"value":"appointments"},"expression":{"range":[56,60,56,115],"value":{"type":"application","application":[{"range":[56,60,56,71],"value":{"type":"functionOrValue","functionOrValue":{"moduleName":["Dict"],"name":"update"}}},{"range":[56,72,56,75],"value":{"type":"functionOrValue","functionOrValue":{"moduleName":[],"name":"key"}}},{"range":[56,76,56,90],"value":{"type":"functionOrValue","functionOrValue":{"moduleName":[],"name":"addAppointment"}}},{"range":[56,102,56,115],"value":{"type":"recordAccess","recordAccess":{"expression":{"range":[56,91,56,102],"value":{"type":"functionOrValue","functionOrValue":{"moduleName":[],"name":"plannerData"}}},"name":{"range":[56,103,56,115],"value":"appointments"}}}}]}}}}]}}}}}}}},{"range":[58,30,58,38],"value":{"type":"recordAccess","recordAccess":{"expression":{"range":[58,25,58,30],"value":{"type":"functionOrValue","functionOrValue":{"moduleName":[],"name":"model"}}},"name":{"range":[58,31,58,38],"value":"planner"}}}}]}}}}}}},{"range":[61,17,69,13],"value":{"type":"function","function":{"documentation":null,"signature":{"range":[61,17,61,64],"value":{"name":{"range":[61,17,61,31],"value":"addAppointment"},"typeAnnotation":{"range":[61,34,61,64],"value":{"type":"function","function":{"left":{"range":[61,34,61,47],"value":{"type":"typed","typed":{"moduleNameAndName":{"range":[61,34,61,39],"value":{"moduleName":[],"name":"Maybe"}},"args":[{"range":[61,40,61,47],"value":{"type":"typed","typed":{"moduleNameAndName":{"range":[61,40,61,47],"value":{"moduleName":[],"name":"Entries"}},"args":[]}}}]}}},"right":{"range":[61,51,61,64],"value":{"type":"typed","typed":{"moduleNameAndName":{"range":[61,51,61,56],"value":{"moduleName":[],"name":"Maybe"}},"args":[{"range":[61,57,61,64],"value":{"type":"typed","typed":{"moduleNameAndName":{"range":[61,57,61,64],"value":{"moduleName":[],"name":"Entries"}},"args":[]}}}]}}}}}}}},"declaration":{"range":[62,17,68,65],"value":{"name":{"range":[62,17,62,31],"value":"addAppointment"},"arguments":[{"range":[62,32,62,39],"value":{"type":"var","var":{"value":"entries"}}}],"expression":{"range":[63,21,68,65],"value":{"type":"case","case":{"cases":[{"pattern":{"range":[64,25,64,42],"value":{"type":"named","named":{"qualified":{"moduleName":[],"name":"Just"},"patterns":[{"range":[64,30,64,42],"value":{"type":"var","var":{"value":"appointments"}}}]}}},"expression":{"range":[65,29,65,92],"value":{"type":"application","application":[{"range":[65,29,65,33],"value":{"type":"functionOrValue","functionOrValue":{"moduleName":[],"name":"Just"}}},{"range":[65,34,65,36],"value":{"type":"operator","operator":"<|"}},{"range":[65,37,65,56],"value":{"type":"functionOrValue","functionOrValue":{"moduleName":[],"name":"listStringToEntries"}}},{"range":[65,57,65,92],"value":{"type":"parenthesized","parenthesized":{"range":[65,70,65,91],"value":{"type":"application","application":[{"range":[65,70,65,78],"value":{"type":"recordAccess","recordAccess":{"expression":{"range":[65,58,65,70],"value":{"type":"functionOrValue","functionOrValue":{"moduleName":[],"name":"appointments"}}},"name":{"range":[65,71,65,78],"value":"entries"}}}},{"range":[65,79,65,81],"value":{"type":"operator","operator":"++"}},{"range":[65,82,65,91],"value":{"type":"list","list":[{"range":[65,84,65,89],"value":{"type":"functionOrValue","functionOrValue":{"moduleName":[],"name":"value"}}}]}}]}}}}]}}},{"pattern":{"range":[67,25,67,32],"value":{"type":"named","named":{"qualified":{"moduleName":[],"name":"Nothing"},"patterns":[]}}},"expression":{"range":[68,29,68,65],"value":{"type":"application","application":[{"range":[68,29,68,33],"value":{"type":"functionOrValue","functionOrValue":{"moduleName":[],"name":"Just"}}},{"range":[68,34,68,65],"value":{"type":"parenthesized","parenthesized":{"range":[68,35,68,64],"value":{"type":"application","application":[{"range":[68,35,68,54],"value":{"type":"functionOrValue","functionOrValue":{"moduleName":[],"name":"listStringToEntries"}}},{"range":[68,55,68,64],"value":{"type":"list","list":[{"range":[68,57,68,62],"value":{"type":"functionOrValue","functionOrValue":{"moduleName":[],"name":"value"}}}]}}]}}}}]}}}],"expression":{"range":[63,26,63,33],"value":{"type":"functionOrValue","functionOrValue":{"moduleName":[],"name":"entries"}}}}}}}}}}}],"expression":{"range":[70,13,72,14],"value":{"type":"tupled","tupled":[{"range":[70,15,70,50],"value":{"type":"recordUpdate","recordUpdate":{"name":{"range":[70,17,70,22],"value":"model"},"updates":[{"range":[70,25,70,49],"value":{"field":{"range":[70,25,70,32],"value":"planner"},"expression":{"range":[70,35,70,48],"value":{"type":"functionOrValue","functionOrValue":{"moduleName":[],"name":"updatePlanner"}}}}}]}}},{"range":[71,15,71,40],"value":{"type":"application","application":[{"range":[71,15,71,26],"value":{"type":"functionOrValue","functionOrValue":{"moduleName":[],"name":"savePlanner"}}},{"range":[71,32,71,40],"value":{"type":"recordAccess","recordAccess":{"expression":{"range":[71,27,71,32],"value":{"type":"functionOrValue","functionOrValue":{"moduleName":[],"name":"model"}}},"name":{"range":[71,33,71,40],"value":"planner"}}}}]}}]}}}}}},{"pattern":{"range":[74,9,74,24],"value":{"type":"named","named":{"qualified":{"moduleName":[],"name":"SaveAppointment"},"patterns":[]}}},"expression":{"range":[75,13,75,49],"value":{"type":"tupled","tupled":[{"range":[75,15,75,20],"value":{"type":"functionOrValue","functionOrValue":{"moduleName":[],"name":"model"}}},{"range":[75,22,75,47],"value":{"type":"application","application":[{"range":[75,22,75,33],"value":{"type":"functionOrValue","functionOrValue":{"moduleName":[],"name":"savePlanner"}}},{"range":[75,39,75,47],"value":{"type":"recordAccess","recordAccess":{"expression":{"range":[75,34,75,39],"value":{"type":"functionOrValue","functionOrValue":{"moduleName":[],"name":"model"}}},"name":{"range":[75,40,75,47],"value":"planner"}}}}]}}]}}},{"pattern":{"range":[77,9,77,42],"value":{"type":"named","named":{"qualified":{"moduleName":[],"name":"AppointmentSaved"},"patterns":[{"range":[77,26,77,42],"value":{"type":"parentisized","parentisized":{"value":{"range":[77,27,77,41],"value":{"type":"named","named":{"qualified":{"moduleName":[],"name":"Ok"},"patterns":[{"range":[77,30,77,41],"value":{"type":"var","var":{"value":"plannerData"}}}]}}}}}}]}}},"expression":{"range":[78,13,86,9],"value":{"type":"let","let":{"declarations":[{"range":[79,17,81,13],"value":{"type":"function","function":{"documentation":null,"signature":null,"declaration":{"range":[79,17,80,51],"value":{"name":{"range":[79,17,79,24],"value":"planner"},"arguments":[],"expression":{"range":[80,21,80,51],"value":{"type":"application","application":[{"range":[80,21,80,39],"value":{"type":"functionOrValue","functionOrValue":{"moduleName":["RemoteData"],"name":"succeed"}}},{"range":[80,40,80,51],"value":{"type":"functionOrValue","functionOrValue":{"moduleName":[],"name":"plannerData"}}}]}}}}}}}],"expression":{"range":[82,13,84,14],"value":{"type":"tupled","tupled":[{"range":[82,15,82,65],"value":{"type":"recordUpdate","recordUpdate":{"name":{"range":[82,17,82,22],"value":"model"},"updates":[{"range":[82,25,82,42],"value":{"field":{"range":[82,25,82,32],"value":"planner"},"expression":{"range":[82,35,82,42],"value":{"type":"functionOrValue","functionOrValue":{"moduleName":[],"name":"planner"}}}}},{"range":[82,44,82,64],"value":{"field":{"range":[82,44,82,53],"value":"saveError"},"expression":{"range":[82,56,82,63],"value":{"type":"functionOrValue","functionOrValue":{"moduleName":[],"name":"Nothing"}}}}}]}}},{"range":[83,15,83,56],"value":{"type":"application","application":[{"range":[83,15,83,28],"value":{"type":"functionOrValue","functionOrValue":{"moduleName":["Route"],"name":"pushUrl"}}},{"range":[83,29,83,43],"value":{"type":"functionOrValue","functionOrValue":{"moduleName":["Route"],"name":"Planners"}}},{"range":[83,49,83,56],"value":{"type":"recordAccess","recordAccess":{"expression":{"range":[83,44,83,49],"value":{"type":"functionOrValue","functionOrValue":{"moduleName":[],"name":"model"}}},"name":{"range":[83,50,83,56],"value":"navKey"}}}}]}}]}}}}}},{"pattern":{"range":[86,9,86,37],"value":{"type":"named","named":{"qualified":{"moduleName":[],"name":"AppointmentSaved"},"patterns":[{"range":[86,26,86,37],"value":{"type":"parentisized","parentisized":{"value":{"range":[86,27,86,36],"value":{"type":"named","named":{"qualified":{"moduleName":[],"name":"Err"},"patterns":[{"range":[86,31,86,36],"value":{"type":"var","var":{"value":"error"}}}]}}}}}}]}}},"expression":{"range":[87,13,89,14],"value":{"type":"tupled","tupled":[{"range":[87,15,87,69],"value":{"type":"recordUpdate","recordUpdate":{"name":{"range":[87,17,87,22],"value":"model"},"updates":[{"range":[87,25,87,68],"value":{"field":{"range":[87,25,87,34],"value":"saveError"},"expression":{"range":[87,37,87,67],"value":{"type":"application","application":[{"range":[87,37,87,41],"value":{"type":"functionOrValue","functionOrValue":{"moduleName":[],"name":"Just"}}},{"range":[87,42,87,67],"value":{"type":"parenthesized","parenthesized":{"range":[87,43,87,66],"value":{"type":"application","application":[{"range":[87,43,87,60],"value":{"type":"functionOrValue","functionOrValue":{"moduleName":[],"name":"buildErrorMessage"}}},{"range":[87,61,87,66],"value":{"type":"functionOrValue","functionOrValue":{"moduleName":[],"name":"error"}}}]}}}}]}}}}]}}},{"range":[88,15,88,23],"value":{"type":"functionOrValue","functionOrValue":{"moduleName":["Cmd"],"name":"none"}}}]}}}],"expression":{"range":[47,10,47,13],"value":{"type":"functionOrValue","functionOrValue":{"moduleName":[],"name":"msg"}}}}}}}}}}},{"range":[92,1,112,21],"value":{"type":"function","function":{"documentation":null,"signature":{"range":[92,1,92,41],"value":{"name":{"range":[92,1,92,12],"value":"savePlanner"},"typeAnnotation":{"range":[92,15,92,41],"value":{"type":"function","function":{"left":{"range":[92,15,92,30],"value":{"type":"typed","typed":{"moduleNameAndName":{"range":[92,15,92,22],"value":{"moduleName":[],"name":"WebData"}},"args":[{"range":[92,23,92,30],"value":{"type":"typed","typed":{"moduleNameAndName":{"range":[92,23,92,30],"value":{"moduleName":[],"name":"Planner"}},"args":[]}}}]}}},"right":{"range":[92,34,92,41],"value":{"type":"typed","typed":{"moduleNameAndName":{"range":[92,34,92,37],"value":{"moduleName":[],"name":"Cmd"}},"args":[{"range":[92,38,92,41],"value":{"type":"typed","typed":{"moduleNameAndName":{"range":[92,38,92,41],"value":{"moduleName":[],"name":"Msg"}},"args":[]}}}]}}}}}}}},"declaration":{"range":[93,1,112,21],"value":{"name":{"range":[93,1,93,12],"value":"savePlanner"},"arguments":[{"range":[93,13,93,20],"value":{"type":"var","var":{"value":"planner"}}}],"expression":{"range":[94,5,112,21],"value":{"type":"case","case":{"cases":[{"pattern":{"range":[95,9,95,39],"value":{"type":"named","named":{"qualified":{"moduleName":["RemoteData"],"name":"Success"},"patterns":[{"range":[95,28,95,39],"value":{"type":"var","var":{"value":"plannerData"}}}]}}},"expression":{"range":[96,13,111,9],"value":{"type":"let","let":{"declarations":[{"range":[97,17,100,13],"value":{"type":"function","function":{"documentation":null,"signature":null,"declaration":{"range":[97,17,99,61],"value":{"name":{"range":[97,17,97,27],"value":"plannerUrl"},"arguments":[],"expression":{"range":[98,21,99,61],"value":{"type":"application","application":[{"range":[98,21,98,54],"value":{"type":"literal","literal":"http://localhost:3001/planners/"}},{"range":[99,25,99,27],"value":{"type":"operator","operator":"++"}},{"range":[99,28,99,46],"value":{"type":"functionOrValue","functionOrValue":{"moduleName":["Planner"],"name":"idToString"}}},{"range":[99,58,99,61],"value":{"type":"recordAccess","recordAccess":{"expression":{"range":[99,47,99,58],"value":{"type":"functionOrValue","functionOrValue":{"moduleName":[],"name":"plannerData"}}},"name":{"range":[99,59,99,61],"value":"id"}}}}]}}}}}}}],"expression":{"range":[101,13,109,18],"value":{"type":"application","application":[{"range":[101,13,101,25],"value":{"type":"functionOrValue","functionOrValue":{"moduleName":["Http"],"name":"request"}}},{"range":[102,17,109,18],"value":{"type":"record","record":[{"range":[102,19,102,35],"value":{"field":{"range":[102,19,102,25],"value":"method"},"expression":{"range":[102,28,102,35],"value":{"type":"literal","literal":"PATCH"}}}},{"range":[103,19,104,17],"value":{"field":{"range":[103,19,103,26],"value":"headers"},"expression":{"range":[103,29,103,31],"value":{"type":"list","list":[]}}}},{"range":[104,19,105,17],"value":{"field":{"range":[104,19,104,22],"value":"url"},"expression":{"range":[104,25,104,35],"value":{"type":"functionOrValue","functionOrValue":{"moduleName":[],"name":"plannerUrl"}}}}},{"range":[105,19,106,17],"value":{"field":{"range":[105,19,105,23],"value":"body"},"expression":{"range":[105,26,105,68],"value":{"type":"application","application":[{"range":[105,26,105,39],"value":{"type":"functionOrValue","functionOrValue":{"moduleName":["Http"],"name":"jsonBody"}}},{"range":[105,40,105,68],"value":{"type":"parenthesized","parenthesized":{"range":[105,41,105,67],"value":{"type":"application","application":[{"range":[105,41,105,55],"value":{"type":"functionOrValue","functionOrValue":{"moduleName":[],"name":"plannerEncoder"}}},{"range":[105,56,105,67],"value":{"type":"functionOrValue","functionOrValue":{"moduleName":[],"name":"plannerData"}}}]}}}}]}}}},{"range":[106,19,107,17],"value":{"field":{"range":[106,19,106,25],"value":"expect"},"expression":{"range":[106,28,106,75],"value":{"type":"application","application":[{"range":[106,28,106,43],"value":{"type":"functionOrValue","functionOrValue":{"moduleName":["Http"],"name":"expectJson"}}},{"range":[106,44,106,60],"value":{"type":"functionOrValue","functionOrValue":{"moduleName":[],"name":"AppointmentSaved"}}},{"range":[106,61,106,75],"value":{"type":"functionOrValue","functionOrValue":{"moduleName":[],"name":"plannerDecoder"}}}]}}}},{"range":[107,19,108,17],"value":{"field":{"range":[107,19,107,26],"value":"timeout"},"expression":{"range":[107,29,107,36],"value":{"type":"functionOrValue","functionOrValue":{"moduleName":[],"name":"Nothing"}}}}},{"range":[108,19,109,17],"value":{"field":{"range":[108,19,108,26],"value":"tracker"},"expression":{"range":[108,29,108,36],"value":{"type":"functionOrValue","functionOrValue":{"moduleName":[],"name":"Nothing"}}}}}]}}]}}}}}},{"pattern":{"range":[111,9,111,10],"value":{"type":"all","all":{}}},"expression":{"range":[112,13,112,21],"value":{"type":"functionOrValue","functionOrValue":{"moduleName":["Cmd"],"name":"none"}}}}],"expression":{"range":[94,10,94,17],"value":{"type":"functionOrValue","functionOrValue":{"moduleName":[],"name":"planner"}}}}}}}}}}},{"range":[115,1,122,10],"value":{"type":"function","function":{"documentation":null,"signature":{"range":[115,1,115,33],"value":{"name":{"range":[115,1,115,13],"value":"fetchPlanner"},"typeAnnotation":{"range":[115,16,115,33],"value":{"type":"function","function":{"left":{"range":[115,16,115,22],"value":{"type":"typed","typed":{"moduleNameAndName":{"range":[115,16,115,22],"value":{"moduleName":[],"name":"String"}},"args":[]}}},"right":{"range":[115,26,115,33],"value":{"type":"typed","typed":{"moduleNameAndName":{"range":[115,26,115,29],"value":{"moduleName":[],"name":"Cmd"}},"args":[{"range":[115,30,115,33],"value":{"type":"typed","typed":{"moduleNameAndName":{"range":[115,30,115,33],"value":{"moduleName":[],"name":"Msg"}},"args":[]}}}]}}}}}}}},"declaration":{"range":[116,1,122,10],"value":{"name":{"range":[116,1,116,13],"value":"fetchPlanner"},"arguments":[{"range":[116,14,116,23],"value":{"type":"var","var":{"value":"plannerId"}}}],"expression":{"range":[117,5,122,10],"value":{"type":"application","application":[{"range":[117,5,117,13],"value":{"type":"functionOrValue","functionOrValue":{"moduleName":["Http"],"name":"get"}}},{"range":[118,9,122,10],"value":{"type":"record","record":[{"range":[118,11,118,63],"value":{"field":{"range":[118,11,118,14],"value":"url"},"expression":{"range":[118,17,118,63],"value":{"type":"application","application":[{"range":[118,17,118,50],"value":{"type":"literal","literal":"http://localhost:3001/planners/"}},{"range":[118,51,118,53],"value":{"type":"operator","operator":"++"}},{"range":[118,54,118,63],"value":{"type":"functionOrValue","functionOrValue":{"moduleName":[],"name":"plannerId"}}}]}}}},{"range":[119,11,122,9],"value":{"field":{"range":[119,11,119,17],"value":"expect"},"expression":{"range":[120,13,121,78],"value":{"type":"application","application":[{"range":[120,13,120,27],"value":{"type":"functionOrValue","functionOrValue":{"moduleName":[],"name":"plannerDecoder"}}},{"range":[121,17,121,19],"value":{"type":"operator","operator":"|>"}},{"range":[121,20,121,35],"value":{"type":"functionOrValue","functionOrValue":{"moduleName":["Http"],"name":"expectJson"}}},{"range":[121,36,121,78],"value":{"type":"parenthesized","parenthesized":{"range":[121,37,121,77],"value":{"type":"application","application":[{"range":[121,37,121,58],"value":{"type":"functionOrValue","functionOrValue":{"moduleName":["RemoteData"],"name":"fromResult"}}},{"range":[121,59,121,61],"value":{"type":"operator","operator":">>"}},{"range":[121,62,121,77],"value":{"type":"functionOrValue","functionOrValue":{"moduleName":[],"name":"PlannerReceived"}}}]}}}}]}}}}]}}]}}}}}}},{"range":[129,1,136,10],"value":{"type":"function","function":{"documentation":null,"signature":{"range":[129,1,129,25],"value":{"name":{"range":[129,1,129,5],"value":"view"},"typeAnnotation":{"range":[129,8,129,25],"value":{"type":"function","function":{"left":{"range":[129,8,129,13],"value":{"type":"typed","typed":{"moduleNameAndName":{"range":[129,8,129,13],"value":{"moduleName":[],"name":"Model"}},"args":[]}}},"right":{"range":[129,17,129,25],"value":{"type":"typed","typed":{"moduleNameAndName":{"range":[129,17,129,21],"value":{"moduleName":[],"name":"Html"}},"args":[{"range":[129,22,129,25],"value":{"type":"typed","typed":{"moduleNameAndName":{"range":[129,22,129,25],"value":{"moduleName":[],"name":"Msg"}},"args":[]}}}]}}}}}}}},"declaration":{"range":[130,1,136,10],"value":{"name":{"range":[130,1,130,5],"value":"view"},"arguments":[{"range":[130,6,130,11],"value":{"type":"var","var":{"value":"model"}}}],"expression":{"range":[131,5,136,10],"value":{"type":"application","application":[{"range":[131,5,131,19],"value":{"type":"functionOrValue","functionOrValue":{"moduleName":["Grid"],"name":"container"}}},{"range":[131,20,131,22],"value":{"type":"list","list":[]}},{"range":[133,9,136,10],"value":{"type":"list","list":[{"range":[133,11,133,21],"value":{"type":"functionOrValue","functionOrValue":{"moduleName":[],"name":"stylesheet"}}},{"range":[134,11,134,36],"value":{"type":"application","application":[{"range":[134,11,134,22],"value":{"type":"functionOrValue","functionOrValue":{"moduleName":[],"name":"viewPlanner"}}},{"range":[134,28,134,36],"value":{"type":"recordAccess","recordAccess":{"expression":{"range":[134,23,134,28],"value":{"type":"functionOrValue","functionOrValue":{"moduleName":[],"name":"model"}}},"name":{"range":[134,29,134,36],"value":"planner"}}}}]}},{"range":[135,11,135,40],"value":{"type":"application","application":[{"range":[135,11,135,24],"value":{"type":"functionOrValue","functionOrValue":{"moduleName":[],"name":"viewSaveError"}}},{"range":[135,30,135,40],"value":{"type":"recordAccess","recordAccess":{"expression":{"range":[135,25,135,30],"value":{"type":"functionOrValue","functionOrValue":{"moduleName":[],"name":"model"}}},"name":{"range":[135,31,135,40],"value":"saveError"}}}}]}}]}}]}}}}}}},{"range":[139,1,155,57],"value":{"type":"function","function":{"documentation":null,"signature":{"range":[139,1,139,42],"value":{"name":{"range":[139,1,139,12],"value":"viewPlanner"},"typeAnnotation":{"range":[139,15,139,42],"value":{"type":"function","function":{"left":{"range":[139,15,139,30],"value":{"type":"typed","typed":{"moduleNameAndName":{"range":[139,15,139,22],"value":{"moduleName":[],"name":"WebData"}},"args":[{"range":[139,23,139,30],"value":{"type":"typed","typed":{"moduleNameAndName":{"range":[139,23,139,30],"value":{"moduleName":[],"name":"Planner"}},"args":[]}}}]}}},"right":{"range":[139,34,139,42],"value":{"type":"typed","typed":{"moduleNameAndName":{"range":[139,34,139,38],"value":{"moduleName":[],"name":"Html"}},"args":[{"range":[139,39,139,42],"value":{"type":"typed","typed":{"moduleNameAndName":{"range":[139,39,139,42],"value":{"moduleName":[],"name":"Msg"}},"args":[]}}}]}}}}}}}},"declaration":{"range":[140,1,155,57],"value":{"name":{"range":[140,1,140,12],"value":"viewPlanner"},"arguments":[{"range":[140,13,140,20],"value":{"type":"var","var":{"value":"planner"}}}],"expression":{"range":[141,5,155,57],"value":{"type":"case","case":{"cases":[{"pattern":{"range":[142,9,142,28],"value":{"type":"named","named":{"qualified":{"moduleName":["RemoteData"],"name":"NotAsked"},"patterns":[]}}},"expression":{"range":[143,13,143,20],"value":{"type":"application","application":[{"range":[143,13,143,17],"value":{"type":"functionOrValue","functionOrValue":{"moduleName":[],"name":"text"}}},{"range":[143,18,143,20],"value":{"type":"literal","literal":""}}]}}},{"pattern":{"range":[145,9,145,27],"value":{"type":"named","named":{"qualified":{"moduleName":["RemoteData"],"name":"Loading"},"patterns":[]}}},"expression":{"range":[146,13,146,40],"value":{"type":"application","application":[{"range":[146,13,146,15],"value":{"type":"functionOrValue","functionOrValue":{"moduleName":[],"name":"h3"}}},{"range":[146,16,146,18],"value":{"type":"list","list":[]}},{"range":[146,19,146,40],"value":{"type":"list","list":[{"range":[146,21,146,38],"value":{"type":"application","application":[{"range":[146,21,146,25],"value":{"type":"functionOrValue","functionOrValue":{"moduleName":[],"name":"text"}}},{"range":[146,26,146,38],"value":{"type":"literal","literal":"Loading..."}}]}}]}}]}}},{"pattern":{"range":[148,9,148,41],"value":{"type":"named","named":{"qualified":{"moduleName":["RemoteData"],"name":"Success"},"patterns":[{"range":[148,28,148,41],"value":{"type":"var","var":{"value":"actualPlanner"}}}]}}},"expression":{"range":[149,13,152,18],"value":{"type":"application","application":[{"range":[149,13,149,16],"value":{"type":"functionOrValue","functionOrValue":{"moduleName":[],"name":"div"}}},{"range":[149,17,149,19],"value":{"type":"list","list":[]}},{"range":[150,17,152,18],"value":{"type":"list","list":[{"range":[150,19,150,91],"value":{"type":"application","application":[{"range":[150,19,150,21],"value":{"type":"functionOrValue","functionOrValue":{"moduleName":[],"name":"h3"}}},{"range":[150,22,150,24],"value":{"type":"list","list":[]}},{"range":[150,25,150,91],"value":{"type":"list","list":[{"range":[150,27,150,89],"value":{"type":"application","application":[{"range":[150,27,150,31],"value":{"type":"functionOrValue","functionOrValue":{"moduleName":[],"name":"text"}}},{"range":[150,32,150,89],"value":{"type":"parenthesized","parenthesized":{"range":[150,33,150,88],"value":{"type":"application","application":[{"range":[150,33,150,49],"value":{"type":"literal","literal":"View Planner: "}},{"range":[150,50,150,52],"value":{"type":"operator","operator":"++"}},{"range":[150,53,150,71],"value":{"type":"functionOrValue","functionOrValue":{"moduleName":["Planner"],"name":"idToString"}}},{"range":[150,85,150,88],"value":{"type":"recordAccess","recordAccess":{"expression":{"range":[150,72,150,85],"value":{"type":"functionOrValue","functionOrValue":{"moduleName":[],"name":"actualPlanner"}}},"name":{"range":[150,86,150,88],"value":"id"}}}}]}}}}]}}]}}]}},{"range":[151,19,151,48],"value":{"type":"application","application":[{"range":[151,19,151,34],"value":{"type":"functionOrValue","functionOrValue":{"moduleName":[],"name":"viewThisPlanner"}}},{"range":[151,35,151,48],"value":{"type":"functionOrValue","functionOrValue":{"moduleName":[],"name":"actualPlanner"}}}]}}]}}]}}},{"pattern":{"range":[154,9,154,37],"value":{"type":"named","named":{"qualified":{"moduleName":["RemoteData"],"name":"Failure"},"patterns":[{"range":[154,28,154,37],"value":{"type":"var","var":{"value":"httpError"}}}]}}},"expression":{"range":[155,13,155,57],"value":{"type":"application","application":[{"range":[155,13,155,27],"value":{"type":"functionOrValue","functionOrValue":{"moduleName":[],"name":"viewFetchError"}}},{"range":[155,28,155,57],"value":{"type":"parenthesized","parenthesized":{"range":[155,29,155,56],"value":{"type":"application","application":[{"range":[155,29,155,46],"value":{"type":"functionOrValue","functionOrValue":{"moduleName":[],"name":"buildErrorMessage"}}},{"range":[155,47,155,56],"value":{"type":"functionOrValue","functionOrValue":{"moduleName":[],"name":"httpError"}}}]}}}}]}}}],"expression":{"range":[141,10,141,17],"value":{"type":"functionOrValue","functionOrValue":{"moduleName":[],"name":"planner"}}}}}}}}}}},{"range":[158,1,171,10],"value":{"type":"function","function":{"documentation":null,"signature":{"range":[158,1,158,38],"value":{"name":{"range":[158,1,158,16],"value":"viewThisPlanner"},"typeAnnotation":{"range":[158,19,158,38],"value":{"type":"function","function":{"left":{"range":[158,19,158,26],"value":{"type":"typed","typed":{"moduleNameAndName":{"range":[158,19,158,26],"value":{"moduleName":[],"name":"Planner"}},"args":[]}}},"right":{"range":[158,30,158,38],"value":{"type":"typed","typed":{"moduleNameAndName":{"range":[158,30,158,34],"value":{"moduleName":[],"name":"Html"}},"args":[{"range":[158,35,158,38],"value":{"type":"typed","typed":{"moduleNameAndName":{"range":[158,35,158,38],"value":{"moduleName":[],"name":"Msg"}},"args":[]}}}]}}}}}}}},"declaration":{"range":[159,1,171,10],"value":{"name":{"range":[159,1,159,16],"value":"viewThisPlanner"},"arguments":[{"range":[159,17,159,24],"value":{"type":"var","var":{"value":"planner"}}}],"expression":{"range":[160,5,171,10],"value":{"type":"application","application":[{"range":[160,5,160,8],"value":{"type":"functionOrValue","functionOrValue":{"moduleName":[],"name":"div"}}},{"range":[160,9,160,11],"value":{"type":"list","list":[]}},{"range":[161,9,171,10],"value":{"type":"list","list":[{"range":[161,11,166,14],"value":{"type":"application","application":[{"range":[161,11,161,20],"value":{"type":"functionOrValue","functionOrValue":{"moduleName":["Html"],"name":"form"}}},{"range":[161,21,161,23],"value":{"type":"list","list":[]}},{"range":[162,13,166,14],"value":{"type":"list","list":[{"range":[162,15,162,23],"value":{"type":"application","application":[{"range":[162,15,162,17],"value":{"type":"functionOrValue","functionOrValue":{"moduleName":[],"name":"br"}}},{"range":[162,18,162,20],"value":{"type":"list","list":[]}},{"range":[162,21,162,23],"value":{"type":"list","list":[]}}]}},{"range":[163,15,165,18],"value":{"type":"application","application":[{"range":[163,15,163,18],"value":{"type":"functionOrValue","functionOrValue":{"moduleName":[],"name":"div"}}},{"range":[163,19,163,21],"value":{"type":"list","list":[]}},{"range":[164,17,165,18],"value":{"type":"list","list":[{"range":[164,19,164,41],"value":{"type":"application","application":[{"range":[164,19,164,33],"value":{"type":"functionOrValue","functionOrValue":{"moduleName":[],"name":"displayPlanner"}}},{"range":[164,34,164,41],"value":{"type":"functionOrValue","functionOrValue":{"moduleName":[],"name":"planner"}}}]}}]}}]}}]}}]}},{"range":[167,11,167,19],"value":{"type":"application","application":[{"range":[167,11,167,13],"value":{"type":"functionOrValue","functionOrValue":{"moduleName":[],"name":"br"}}},{"range":[167,14,167,16],"value":{"type":"list","list":[]}},{"range":[167,17,167,19],"value":{"type":"list","list":[]}}]}},{"range":[168,11,170,43],"value":{"type":"application","application":[{"range":[168,11,168,14],"value":{"type":"functionOrValue","functionOrValue":{"moduleName":[],"name":"div"}}},{"range":[169,13,169,15],"value":{"type":"list","list":[]}},{"range":[170,13,170,43],"value":{"type":"list","list":[{"range":[170,15,170,41],"value":{"type":"application","application":[{"range":[170,15,170,33],"value":{"type":"functionOrValue","functionOrValue":{"moduleName":[],"name":"displayAppointment"}}},{"range":[170,34,170,41],"value":{"type":"functionOrValue","functionOrValue":{"moduleName":[],"name":"planner"}}}]}}]}}]}}]}}]}}}}}}},{"range":[174,1,177,21],"value":{"type":"function","function":{"documentation":null,"signature":{"range":[174,1,174,31],"value":{"name":{"range":[174,1,174,10],"value":"viewValue"},"typeAnnotation":{"range":[174,13,174,31],"value":{"type":"function","function":{"left":{"range":[174,13,174,19],"value":{"type":"typed","typed":{"moduleNameAndName":{"range":[174,13,174,19],"value":{"moduleName":[],"name":"String"}},"args":[]}}},"right":{"range":[174,23,174,31],"value":{"type":"typed","typed":{"moduleNameAndName":{"range":[174,23,174,27],"value":{"moduleName":[],"name":"Html"}},"args":[{"range":[174,28,174,31],"value":{"type":"typed","typed":{"moduleNameAndName":{"range":[174,28,174,31],"value":{"moduleName":[],"name":"Msg"}},"args":[]}}}]}}}}}}}},"declaration":{"range":[175,1,177,21],"value":{"name":{"range":[175,1,175,10],"value":"viewValue"},"arguments":[{"range":[175,11,175,14],"value":{"type":"var","var":{"value":"key"}}}],"expression":{"range":[176,5,177,21],"value":{"type":"application","application":[{"range":[176,5,176,8],"value":{"type":"functionOrValue","functionOrValue":{"moduleName":[],"name":"div"}}},{"range":[176,9,176,38],"value":{"type":"list","list":[{"range":[176,11,176,36],"value":{"type":"application","application":[{"range":[176,11,176,16],"value":{"type":"functionOrValue","functionOrValue":{"moduleName":[],"name":"class"}}},{"range":[176,17,176,36],"value":{"type":"literal","literal":"col-xs-6 col-md-6"}}]}}]}},{"range":[177,9,177,21],"value":{"type":"list","list":[{"range":[177,11,177,19],"value":{"type":"application","application":[{"range":[177,11,177,15],"value":{"type":"functionOrValue","functionOrValue":{"moduleName":[],"name":"text"}}},{"range":[177,16,177,19],"value":{"type":"functionOrValue","functionOrValue":{"moduleName":[],"name":"key"}}}]}}]}}]}}}}}}},{"range":[180,1,192,10],"value":{"type":"function","function":{"documentation":null,"signature":{"range":[180,1,180,42],"value":{"name":{"range":[180,1,180,16],"value":"viewButtonValue"},"typeAnnotation":{"range":[180,19,180,42],"value":{"type":"function","function":{"left":{"range":[180,19,180,30],"value":{"type":"typed","typed":{"moduleNameAndName":{"range":[180,19,180,30],"value":{"moduleName":[],"name":"Appointment"}},"args":[]}}},"right":{"range":[180,34,180,42],"value":{"type":"typed","typed":{"moduleNameAndName":{"range":[180,34,180,38],"value":{"moduleName":[],"name":"Html"}},"args":[{"range":[180,39,180,42],"value":{"type":"typed","typed":{"moduleNameAndName":{"range":[180,39,180,42],"value":{"moduleName":[],"name":"Msg"}},"args":[]}}}]}}}}}}}},"declaration":{"range":[181,1,192,10],"value":{"name":{"range":[181,1,181,16],"value":"viewButtonValue"},"arguments":[{"range":[181,17,181,28],"value":{"type":"var","var":{"value":"appointment"}}}],"expression":{"range":[182,5,192,10],"value":{"type":"application","application":[{"range":[182,5,182,8],"value":{"type":"functionOrValue","functionOrValue":{"moduleName":[],"name":"div"}}},{"range":[182,9,182,38],"value":{"type":"list","list":[{"range":[182,11,182,36],"value":{"type":"application","application":[{"range":[182,11,182,16],"value":{"type":"functionOrValue","functionOrValue":{"moduleName":[],"name":"class"}}},{"range":[182,17,182,36],"value":{"type":"literal","literal":"col-xs-6 col-md-6"}}]}}]}},{"range":[183,9,192,10],"value":{"type":"list","list":[{"range":[183,11,191,39],"value":{"type":"application","application":[{"range":[183,11,183,24],"value":{"type":"functionOrValue","functionOrValue":{"moduleName":["Button"],"name":"button"}}},{"range":[184,13,190,14],"value":{"type":"list","list":[{"range":[184,15,184,27],"value":{"type":"functionOrValue","functionOrValue":{"moduleName":["Button"],"name":"light"}}},{"range":[185,15,185,27],"value":{"type":"functionOrValue","functionOrValue":{"moduleName":["Button"],"name":"large"}}},{"range":[186,15,186,27],"value":{"type":"functionOrValue","functionOrValue":{"moduleName":["Button"],"name":"block"}}},{"range":[189,15,189,97],"value":{"type":"application","application":[{"range":[189,15,189,27],"value":{"type":"functionOrValue","functionOrValue":{"moduleName":["Button"],"name":"attrs"}}},{"range":[189,28,189,97],"value":{"type":"list","list":[{"range":[189,30,189,95],"value":{"type":"application","application":[{"range":[189,30,189,41],"value":{"type":"functionOrValue","functionOrValue":{"moduleName":[],"name":"onMouseOver"}}},{"range":[189,42,189,95],"value":{"type":"parenthesized","parenthesized":{"range":[189,43,189,94],"value":{"type":"application","application":[{"range":[189,43,189,60],"value":{"type":"functionOrValue","functionOrValue":{"moduleName":[],"name":"SelectAppointment"}}},{"range":[189,72,189,76],"value":{"type":"recordAccess","recordAccess":{"expression":{"range":[189,61,189,72],"value":{"type":"functionOrValue","functionOrValue":{"moduleName":[],"name":"appointment"}}},"name":{"range":[189,73,189,76],"value":"key"}}}},{"range":[189,88,189,94],"value":{"type":"recordAccess","recordAccess":{"expression":{"range":[189,77,189,88],"value":{"type":"functionOrValue","functionOrValue":{"moduleName":[],"name":"appointment"}}},"name":{"range":[189,89,189,94],"value":"value"}}}}]}}}}]}}]}}]}}]}},{"range":[191,13,191,39],"value":{"type":"list","list":[{"range":[191,15,191,37],"value":{"type":"application","application":[{"range":[191,15,191,19],"value":{"type":"functionOrValue","functionOrValue":{"moduleName":[],"name":"text"}}},{"range":[191,31,191,37],"value":{"type":"recordAccess","recordAccess":{"expression":{"range":[191,20,191,31],"value":{"type":"functionOrValue","functionOrValue":{"moduleName":[],"name":"appointment"}}},"name":{"range":[191,32,191,37],"value":"value"}}}}]}}]}}]}}]}}]}}}}}}},{"range":[195,1,211,1],"value":{"type":"function","function":{"documentation":null,"signature":{"range":[195,1,195,37],"value":{"name":{"range":[195,1,195,15],"value":"displayPlanner"},"typeAnnotation":{"range":[195,18,195,37],"value":{"type":"function","function":{"left":{"range":[195,18,195,25],"value":{"type":"typed","typed":{"moduleNameAndName":{"range":[195,18,195,25],"value":{"moduleName":[],"name":"Planner"}},"args":[]}}},"right":{"range":[195,29,195,37],"value":{"type":"typed","typed":{"moduleNameAndName":{"range":[195,29,195,33],"value":{"moduleName":[],"name":"Html"}},"args":[{"range":[195,34,195,37],"value":{"type":"typed","typed":{"moduleNameAndName":{"range":[195,34,195,37],"value":{"moduleName":[],"name":"Msg"}},"args":[]}}}]}}}}}}}},"declaration":{"range":[196,1,211,1],"value":{"name":{"range":[196,1,196,15],"value":"displayPlanner"},"arguments":[{"range":[196,16,196,23],"value":{"type":"var","var":{"value":"planner"}}}],"expression":{"range":[197,5,211,1],"value":{"type":"let","let":{"declarations":[{"range":[198,9,203,5],"value":{"type":"function","function":{"documentation":null,"signature":null,"declaration":{"range":[198,9,202,18],"value":{"name":{"range":[198,9,198,15],"value":"viewer"},"arguments":[{"range":[198,16,198,29],"value":{"type":"tuple","tuple":{"value":[{"range":[198,18,198,21],"value":{"type":"var","var":{"value":"key"}}},{"range":[198,23,198,27],"value":{"type":"var","var":{"value":"data"}}}]}}}],"expression":{"range":[199,13,202,18],"value":{"type":"application","application":[{"range":[199,13,199,16],"value":{"type":"functionOrValue","functionOrValue":{"moduleName":[],"name":"div"}}},{"range":[199,17,199,19],"value":{"type":"list","list":[]}},{"range":[200,17,202,18],"value":{"type":"list","list":[{"range":[200,19,200,64],"value":{"type":"application","application":[{"range":[200,19,200,21],"value":{"type":"functionOrValue","functionOrValue":{"moduleName":[],"name":"h2"}}},{"range":[200,22,200,51],"value":{"type":"list","list":[{"range":[200,24,200,49],"value":{"type":"application","application":[{"range":[200,24,200,29],"value":{"type":"functionOrValue","functionOrValue":{"moduleName":[],"name":"class"}}},{"range":[200,30,200,49],"value":{"type":"literal","literal":"row, text-primary"}}]}}]}},{"range":[200,52,200,64],"value":{"type":"list","list":[{"range":[200,54,200,62],"value":{"type":"application","application":[{"range":[200,54,200,58],"value":{"type":"functionOrValue","functionOrValue":{"moduleName":[],"name":"text"}}},{"range":[200,59,200,62],"value":{"type":"functionOrValue","functionOrValue":{"moduleName":[],"name":"key"}}}]}}]}}]}},{"range":[201,19,201,63],"value":{"type":"application","application":[{"range":[201,19,201,30],"value":{"type":"functionOrValue","functionOrValue":{"moduleName":[],"name":"displayData"}}},{"range":[201,31,201,34],"value":{"type":"functionOrValue","functionOrValue":{"moduleName":[],"name":"key"}}},{"range":[201,35,201,63],"value":{"type":"parenthesized","parenthesized":{"range":[201,36,201,62],"value":{"type":"application","application":[{"range":[201,36,201,57],"value":{"type":"functionOrValue","functionOrValue":{"moduleName":["Planner"],"name":"entriesToList"}}},{"range":[201,58,201,62],"value":{"type":"functionOrValue","functionOrValue":{"moduleName":[],"name":"data"}}}]}}}}]}}]}}]}}}}}}}],"expression":{"range":[204,5,208,10],"value":{"type":"application","application":[{"range":[204,5,204,8],"value":{"type":"functionOrValue","functionOrValue":{"moduleName":[],"name":"div"}}},{"range":[204,9,204,11],"value":{"type":"list","list":[]}},{"range":[205,9,208,10],"value":{"type":"parenthesized","parenthesized":{"range":[205,10,207,31],"value":{"type":"application","application":[{"range":[205,10,205,34],"value":{"type":"functionOrValue","functionOrValue":{"moduleName":["Planner"],"name":"getAvailableDays"}}},{"range":[205,35,205,42],"value":{"type":"functionOrValue","functionOrValue":{"moduleName":[],"name":"planner"}}},{"range":[206,13,206,15],"value":{"type":"operator","operator":"|>"}},{"range":[206,16,206,27],"value":{"type":"functionOrValue","functionOrValue":{"moduleName":["Dict"],"name":"toList"}}},{"range":[207,13,207,15],"value":{"type":"operator","operator":"|>"}},{"range":[207,16,207,24],"value":{"type":"functionOrValue","functionOrValue":{"moduleName":["List"],"name":"map"}}},{"range":[207,25,207,31],"value":{"type":"functionOrValue","functionOrValue":{"moduleName":[],"name":"viewer"}}}]}}}}]}}}}}}}}}},{"range":[211,1,213,124],"value":{"type":"function","function":{"documentation":null,"signature":{"range":[211,1,211,48],"value":{"name":{"range":[211,1,211,12],"value":"displayData"},"typeAnnotation":{"range":[211,15,211,48],"value":{"type":"function","function":{"left":{"range":[211,15,211,21],"value":{"type":"typed","typed":{"moduleNameAndName":{"range":[211,15,211,21],"value":{"moduleName":[],"name":"String"}},"args":[]}}},"right":{"range":[211,25,211,48],"value":{"type":"function","function":{"left":{"range":[211,25,211,36],"value":{"type":"typed","typed":{"moduleNameAndName":{"range":[211,25,211,29],"value":{"moduleName":[],"name":"List"}},"args":[{"range":[211,30,211,36],"value":{"type":"typed","typed":{"moduleNameAndName":{"range":[211,30,211,36],"value":{"moduleName":[],"name":"String"}},"args":[]}}}]}}},"right":{"range":[211,40,211,48],"value":{"type":"typed","typed":{"moduleNameAndName":{"range":[211,40,211,44],"value":{"moduleName":[],"name":"Html"}},"args":[{"range":[211,45,211,48],"value":{"type":"typed","typed":{"moduleNameAndName":{"range":[211,45,211,48],"value":{"moduleName":[],"name":"Msg"}},"args":[]}}}]}}}}}}}}}}},"declaration":{"range":[212,1,213,124],"value":{"name":{"range":[212,1,212,12],"value":"displayData"},"arguments":[{"range":[212,13,212,16],"value":{"type":"var","var":{"value":"key"}}},{"range":[212,17,212,21],"value":{"type":"var","var":{"value":"data"}}}],"expression":{"range":[213,5,213,124],"value":{"type":"application","application":[{"range":[213,5,213,13],"value":{"type":"functionOrValue","functionOrValue":{"moduleName":["List"],"name":"map"}}},{"range":[213,14,213,29],"value":{"type":"functionOrValue","functionOrValue":{"moduleName":[],"name":"viewButtonValue"}}},{"range":[213,30,213,101],"value":{"type":"parenthesized","parenthesized":{"range":[213,31,213,100],"value":{"type":"application","application":[{"range":[213,31,213,63],"value":{"type":"functionOrValue","functionOrValue":{"moduleName":["Planner"],"name":"toAppointmentListWithKey"}}},{"range":[213,64,213,67],"value":{"type":"functionOrValue","functionOrValue":{"moduleName":[],"name":"key"}}},{"range":[213,68,213,100],"value":{"type":"parenthesized","parenthesized":{"range":[213,69,213,99],"value":{"type":"application","application":[{"range":[213,69,213,94],"value":{"type":"functionOrValue","functionOrValue":{"moduleName":["Planner"],"name":"toAppointmentList"}}},{"range":[213,95,213,99],"value":{"type":"functionOrValue","functionOrValue":{"moduleName":[],"name":"data"}}}]}}}}]}}}},{"range":[213,102,213,104],"value":{"type":"operator","operator":"|>"}},{"range":[213,105,213,108],"value":{"type":"functionOrValue","functionOrValue":{"moduleName":[],"name":"div"}}},{"range":[213,109,213,124],"value":{"type":"list","list":[{"range":[213,111,213,122],"value":{"type":"application","application":[{"range":[213,111,213,116],"value":{"type":"functionOrValue","functionOrValue":{"moduleName":[],"name":"class"}}},{"range":[213,117,213,122],"value":{"type":"literal","literal":"row"}}]}}]}}]}}}}}}},{"range":[220,1,236,1],"value":{"type":"function","function":{"documentation":null,"signature":{"range":[220,1,220,41],"value":{"name":{"range":[220,1,220,19],"value":"displayAppointment"},"typeAnnotation":{"range":[220,22,220,41],"value":{"type":"function","function":{"left":{"range":[220,22,220,29],"value":{"type":"typed","typed":{"moduleNameAndName":{"range":[220,22,220,29],"value":{"moduleName":[],"name":"Planner"}},"args":[]}}},"right":{"range":[220,33,220,41],"value":{"type":"typed","typed":{"moduleNameAndName":{"range":[220,33,220,37],"value":{"moduleName":[],"name":"Html"}},"args":[{"range":[220,38,220,41],"value":{"type":"typed","typed":{"moduleNameAndName":{"range":[220,38,220,41],"value":{"moduleName":[],"name":"Msg"}},"args":[]}}}]}}}}}}}},"declaration":{"range":[221,1,236,1],"value":{"name":{"range":[221,1,221,19],"value":"displayAppointment"},"arguments":[{"range":[221,20,221,27],"value":{"type":"var","var":{"value":"planner"}}}],"expression":{"range":[222,5,236,1],"value":{"type":"let","let":{"declarations":[{"range":[223,9,228,5],"value":{"type":"function","function":{"documentation":null,"signature":null,"declaration":{"range":[223,9,227,18],"value":{"name":{"range":[223,9,223,15],"value":"viewer"},"arguments":[{"range":[223,16,223,29],"value":{"type":"tuple","tuple":{"value":[{"range":[223,18,223,21],"value":{"type":"var","var":{"value":"key"}}},{"range":[223,23,223,27],"value":{"type":"var","var":{"value":"data"}}}]}}}],"expression":{"range":[224,13,227,18],"value":{"type":"application","application":[{"range":[224,13,224,16],"value":{"type":"functionOrValue","functionOrValue":{"moduleName":[],"name":"div"}}},{"range":[224,17,224,19],"value":{"type":"list","list":[]}},{"range":[225,17,227,18],"value":{"type":"list","list":[{"range":[225,19,225,64],"value":{"type":"application","application":[{"range":[225,19,225,21],"value":{"type":"functionOrValue","functionOrValue":{"moduleName":[],"name":"h2"}}},{"range":[225,22,225,51],"value":{"type":"list","list":[{"range":[225,24,225,49],"value":{"type":"application","application":[{"range":[225,24,225,29],"value":{"type":"functionOrValue","functionOrValue":{"moduleName":[],"name":"class"}}},{"range":[225,30,225,49],"value":{"type":"literal","literal":"row, text-primary"}}]}}]}},{"range":[225,52,225,64],"value":{"type":"list","list":[{"range":[225,54,225,62],"value":{"type":"application","application":[{"range":[225,54,225,58],"value":{"type":"functionOrValue","functionOrValue":{"moduleName":[],"name":"text"}}},{"range":[225,59,225,62],"value":{"type":"functionOrValue","functionOrValue":{"moduleName":[],"name":"key"}}}]}}]}}]}},{"range":[226,19,226,89],"value":{"type":"application","application":[{"range":[226,19,226,27],"value":{"type":"functionOrValue","functionOrValue":{"moduleName":["List"],"name":"map"}}},{"range":[226,28,226,37],"value":{"type":"functionOrValue","functionOrValue":{"moduleName":[],"name":"viewValue"}}},{"range":[226,38,226,66],"value":{"type":"parenthesized","parenthesized":{"range":[226,39,226,65],"value":{"type":"application","application":[{"range":[226,39,226,60],"value":{"type":"functionOrValue","functionOrValue":{"moduleName":["Planner"],"name":"entriesToList"}}},{"range":[226,61,226,65],"value":{"type":"functionOrValue","functionOrValue":{"moduleName":[],"name":"data"}}}]}}}},{"range":[226,67,226,69],"value":{"type":"operator","operator":"|>"}},{"range":[226,70,226,73],"value":{"type":"functionOrValue","functionOrValue":{"moduleName":[],"name":"div"}}},{"range":[226,74,226,89],"value":{"type":"list","list":[{"range":[226,76,226,87],"value":{"type":"application","application":[{"range":[226,76,226,81],"value":{"type":"functionOrValue","functionOrValue":{"moduleName":[],"name":"class"}}},{"range":[226,82,226,87],"value":{"type":"literal","literal":"row"}}]}}]}}]}}]}}]}}}}}}}],"expression":{"range":[229,5,233,10],"value":{"type":"application","application":[{"range":[229,5,229,8],"value":{"type":"functionOrValue","functionOrValue":{"moduleName":[],"name":"div"}}},{"range":[229,9,229,11],"value":{"type":"list","list":[]}},{"range":[230,9,233,10],"value":{"type":"parenthesized","parenthesized":{"range":[230,10,232,31],"value":{"type":"application","application":[{"range":[230,10,230,33],"value":{"type":"functionOrValue","functionOrValue":{"moduleName":["Planner"],"name":"getAppointments"}}},{"range":[230,34,230,41],"value":{"type":"functionOrValue","functionOrValue":{"moduleName":[],"name":"planner"}}},{"range":[231,13,231,15],"value":{"type":"operator","operator":"|>"}},{"range":[231,16,231,27],"value":{"type":"functionOrValue","functionOrValue":{"moduleName":["Dict"],"name":"toList"}}},{"range":[232,13,232,15],"value":{"type":"operator","operator":"|>"}},{"range":[232,16,232,24],"value":{"type":"functionOrValue","functionOrValue":{"moduleName":["List"],"name":"map"}}},{"range":[232,25,232,31],"value":{"type":"functionOrValue","functionOrValue":{"moduleName":[],"name":"viewer"}}}]}}}}]}}}}}}}}}},{"range":[236,1,248,1],"value":{"type":"function","function":{"documentation":null,"signature":{"range":[236,1,236,36],"value":{"name":{"range":[236,1,236,15],"value":"viewFetchError"},"typeAnnotation":{"range":[236,18,236,36],"value":{"type":"function","function":{"left":{"range":[236,18,236,24],"value":{"type":"typed","typed":{"moduleNameAndName":{"range":[236,18,236,24],"value":{"moduleName":[],"name":"String"}},"args":[]}}},"right":{"range":[236,28,236,36],"value":{"type":"typed","typed":{"moduleNameAndName":{"range":[236,28,236,32],"value":{"moduleName":[],"name":"Html"}},"args":[{"range":[236,33,236,36],"value":{"type":"typed","typed":{"moduleNameAndName":{"range":[236,33,236,36],"value":{"moduleName":[],"name":"Msg"}},"args":[]}}}]}}}}}}}},"declaration":{"range":[237,1,248,1],"value":{"name":{"range":[237,1,237,15],"value":"viewFetchError"},"arguments":[{"range":[237,16,237,28],"value":{"type":"var","var":{"value":"errorMessage"}}}],"expression":{"range":[238,5,248,1],"value":{"type":"let","let":{"declarations":[{"range":[239,9,241,5],"value":{"type":"function","function":{"documentation":null,"signature":null,"declaration":{"range":[239,9,240,51],"value":{"name":{"range":[239,9,239,21],"value":"errorHeading"},"arguments":[],"expression":{"range":[240,13,240,51],"value":{"type":"literal","literal":"Couldn't fetch planner at this time."}}}}}}}],"expression":{"range":[242,5,245,10],"value":{"type":"application","application":[{"range":[242,5,242,8],"value":{"type":"functionOrValue","functionOrValue":{"moduleName":[],"name":"div"}}},{"range":[242,9,242,11],"value":{"type":"list","list":[]}},{"range":[243,9,245,10],"value":{"type":"list","list":[{"range":[243,11,243,38],"value":{"type":"application","application":[{"range":[243,11,243,13],"value":{"type":"functionOrValue","functionOrValue":{"moduleName":[],"name":"h3"}}},{"range":[243,14,243,16],"value":{"type":"list","list":[]}},{"range":[243,17,243,38],"value":{"type":"list","list":[{"range":[243,19,243,36],"value":{"type":"application","application":[{"range":[243,19,243,23],"value":{"type":"functionOrValue","functionOrValue":{"moduleName":[],"name":"text"}}},{"range":[243,24,243,36],"value":{"type":"functionOrValue","functionOrValue":{"moduleName":[],"name":"errorHeading"}}}]}}]}}]}},{"range":[244,11,244,43],"value":{"type":"application","application":[{"range":[244,11,244,15],"value":{"type":"functionOrValue","functionOrValue":{"moduleName":[],"name":"text"}}},{"range":[244,16,244,43],"value":{"type":"parenthesized","parenthesized":{"range":[244,17,244,42],"value":{"type":"application","application":[{"range":[244,17,244,26],"value":{"type":"literal","literal":"Error: "}},{"range":[244,27,244,29],"value":{"type":"operator","operator":"++"}},{"range":[244,30,244,42],"value":{"type":"functionOrValue","functionOrValue":{"moduleName":[],"name":"errorMessage"}}}]}}}}]}}]}}]}}}}}}}}}},{"range":[248,1,258,20],"value":{"type":"function","function":{"documentation":null,"signature":{"range":[248,1,248,41],"value":{"name":{"range":[248,1,248,14],"value":"viewSaveError"},"typeAnnotation":{"range":[248,17,248,41],"value":{"type":"function","function":{"left":{"range":[248,17,248,29],"value":{"type":"typed","typed":{"moduleNameAndName":{"range":[248,17,248,22],"value":{"moduleName":[],"name":"Maybe"}},"args":[{"range":[248,23,248,29],"value":{"type":"typed","typed":{"moduleNameAndName":{"range":[248,23,248,29],"value":{"moduleName":[],"name":"String"}},"args":[]}}}]}}},"right":{"range":[248,33,248,41],"value":{"type":"typed","typed":{"moduleNameAndName":{"range":[248,33,248,37],"value":{"moduleName":[],"name":"Html"}},"args":[{"range":[248,38,248,41],"value":{"type":"generic","generic":{"value":"msg"}}}]}}}}}}}},"declaration":{"range":[249,1,258,20],"value":{"name":{"range":[249,1,249,14],"value":"viewSaveError"},"arguments":[{"range":[249,15,249,25],"value":{"type":"var","var":{"value":"maybeError"}}}],"expression":{"range":[250,5,258,20],"value":{"type":"case","case":{"cases":[{"pattern":{"range":[251,9,251,19],"value":{"type":"named","named":{"qualified":{"moduleName":[],"name":"Just"},"patterns":[{"range":[251,14,251,19],"value":{"type":"var","var":{"value":"error"}}}]}}},"expression":{"range":[252,13,255,18],"value":{"type":"application","application":[{"range":[252,13,252,16],"value":{"type":"functionOrValue","functionOrValue":{"moduleName":[],"name":"div"}}},{"range":[252,17,252,19],"value":{"type":"list","list":[]}},{"range":[253,17,255,18],"value":{"type":"list","list":[{"range":[253,19,253,75],"value":{"type":"application","application":[{"range":[253,19,253,21],"value":{"type":"functionOrValue","functionOrValue":{"moduleName":[],"name":"h3"}}},{"range":[253,22,253,24],"value":{"type":"list","list":[]}},{"range":[253,25,253,75],"value":{"type":"list","list":[{"range":[253,27,253,73],"value":{"type":"application","application":[{"range":[253,27,253,31],"value":{"type":"functionOrValue","functionOrValue":{"moduleName":[],"name":"text"}}},{"range":[253,32,253,73],"value":{"type":"literal","literal":"Couldn't take appointment at this time."}}]}}]}}]}},{"range":[254,19,254,44],"value":{"type":"application","application":[{"range":[254,19,254,23],"value":{"type":"functionOrValue","functionOrValue":{"moduleName":[],"name":"text"}}},{"range":[254,24,254,44],"value":{"type":"parenthesized","parenthesized":{"range":[254,25,254,43],"value":{"type":"application","application":[{"range":[254,25,254,34],"value":{"type":"literal","literal":"Error: "}},{"range":[254,35,254,37],"value":{"type":"operator","operator":"++"}},{"range":[254,38,254,43],"value":{"type":"functionOrValue","functionOrValue":{"moduleName":[],"name":"error"}}}]}}}}]}}]}}]}}},{"pattern":{"range":[257,9,257,16],"value":{"type":"named","named":{"qualified":{"moduleName":[],"name":"Nothing"},"patterns":[]}}},"expression":{"range":[258,13,258,20],"value":{"type":"application","application":[{"range":[258,13,258,17],"value":{"type":"functionOrValue","functionOrValue":{"moduleName":[],"name":"text"}}},{"range":[258,18,258,20],"value":{"type":"literal","literal":""}}]}}}],"expression":{"range":[250,10,250,20],"value":{"type":"functionOrValue","functionOrValue":{"moduleName":[],"name":"maybeError"}}}}}}}}}}}],"comments":[{"range":[217,1,217,57],"value":"--  List.map viewButtonValue data |> div [ class \"row\" ]"},{"range":[188,13,188,65],"value":"-- , Button.attrs [ Button.onClick SaveAppointment ]"},{"range":[133,22,133,67],"value":"-- Inlined Bootstrap CSS for use with reactor"},{"range":[132,9,132,44],"value":"-- Responsive fixed width container"},{"range":[126,1,126,9],"value":"-- VIEWS"},{"range":[60,17,60,107],"value":"--  { oldPlanner | appointments = Dict.update key addAppointment oldPlanner.appointments }"}]}